wanghe20/__init__.py
wanghe20/hello.py
wanghe20/models.py
wanghe20/templates/hello.html
wanghe20/templates/login.html
wanghe20/templates/upload.html
wanghe20/templates/admin/index.html
wanghe20-0.3.dist-info/METADATA
wanghe20-0.3.dist-info/WHEEL
wanghe20-0.3.dist-info/entry_points.txt
wanghe20-0.3.dist-info/top_level.txt
wanghe20-0.3.dist-info/RECORD
