Metadata-Version: 2.1
Name: wanghe20
Version: 0.3
Summary: UNKNOWN
Home-page: http://url.com
Author: luzg
Author-email: zhiguo.lu@163.com
License: UNKNOWN
Platform: UNKNOWN
Requires-Dist: Flask-Admin (>=1.6)
Requires-Dist: Flask (>=2)
